geov/__init__.py
geov/config.py
geov/model.py
geov/tokenizer.py
geov-0.0.2.dist-info/METADATA
geov-0.0.2.dist-info/WHEEL
geov-0.0.2.dist-info/top_level.txt
geov-0.0.2.dist-info/RECORD
