Metadata-Version: 2.1
Name: geov
Version: 0.0.2
Summary: The GeoV model is a large langauge model designed by Georges Harik and uses Rotary Positional Embeddings with Relative distances (RoPER). We have shared a pretrained 9B parameter model.
Home-page: https://github.com/geov-ai/geov
Author: Better Planet Investments and labml.ai
Author-email: contact@labml.ai
License: UNKNOWN
Keywords: machine learning
Platform: UNKNOWN
Classifier: Programming Language :: Python :: 3
Classifier: License :: OSI Approved :: Apache Software License
Classifier: Intended Audience :: Developers
Classifier: Intended Audience :: Science/Research
Classifier: Topic :: Scientific/Engineering :: Artificial Intelligence
Requires-Dist: transformers
Requires-Dist: torch
Requires-Dist: sentencepiece
